knot0_types_v2/__init__.py
knot0_types_v2/application.py
knot0_types_v2/component.py
knot0_types_v2/dataasset.py
knot0_types_v2/datatype.py
knot0_types_v2/event.py
knot0_types_v2/infrastructure.py
knot0_types_v2/policy.py
knot0_types_v2/system.py
knot0_types_v2/workflow.py
knot0_types-2.0.0.dist-info/METADATA
knot0_types-2.0.0.dist-info/WHEEL
knot0_types-2.0.0.dist-info/top_level.txt
knot0_types-2.0.0.dist-info/RECORD
