Metadata-Version: 2.4
Name: knot0-types
Version: 2.0.0
Summary: Prebuilt Pydantic models generated from Knot0 JSON Schemas
License: MIT
Requires-Python: >=3.9
Requires-Dist: pydantic<3,>=1.10
